forge/__init__.py
forge/forge.py
forge/core/logging.py
forge/core/templates/robots.txt
forge/core/templates/sitemap.xml
forge/gen/__init__.py
forge/gen/enum.py
forge/gen/fn.py
forge/gen/health.py
forge/gen/metadata.py
forge/gen/table.py
forge/gen/view.py
forge/tools/db.py
forge/tools/model.py
forge/tools/sql_mapping.py
forge/tools/auth/__init__.py
forge/tools/auth/jwt.py
forge/tools/auth/oauth.py
api_forge-0.1.1.dist-info/METADATA
api_forge-0.1.1.dist-info/WHEEL
api_forge-0.1.1.dist-info/licenses/LICENSE
api_forge-0.1.1.dist-info/RECORD
