Metadata-Version: 2.4
Name: api-forge
Version: 0.1.1
Summary: Add your description here
Author-email: Fernando Bryan Reza Campos <fer.rezac@outlook.com>
License-File: LICENSE
Classifier: Development Status :: 7 - Inactive
Classifier: Intended Audience :: Developers
Classifier: Programming Language :: Python :: 3.10
Classifier: Programming Language :: Python :: 3.11
Classifier: Programming Language :: Python :: 3.12
Classifier: Topic :: Database
Classifier: Topic :: Internet :: WWW/HTTP :: WSGI :: Application
Classifier: Topic :: Software Development :: Code Generators
Classifier: Typing :: Typed
Requires-Python: >=3.10
Requires-Dist: fastapi>=0.115.13
Requires-Dist: psycopg2>=2.9.10
Requires-Dist: pydantic>=2.11.7
Requires-Dist: sqlalchemy>=2.0.41
